{
    "interactionModel": {
        "languageModel": {
            "invocationName": "mein mercedes",
            "intents": [
                {
                    "name": "AMAZON.CancelIntent",
                    "samples": []
        },
                {
                    "name": "AMAZON.HelpIntent",
                    "samples": []
        },
                {
                    "name": "AMAZON.StopIntent",
                    "samples": []
        },
                {
                    "name": "GetFuelLevelIntent",
                    "samples": [
            "sage mir den benzin stand",
            "wie viel benzin ist im tank",
            "wie viel sprit ist im tank",
            "wie viel benzin habe ich",
            "muss ich tanken",
            "wie viel benzin ist im auto",
            "wie viel sprit ist im auto",
            "wie viel benzin ist in meinem mercedes",
            "wie viel sprit ist in meinem mercedes",
            "was ist der benzin stand"
          ]
        },
                {
                    "name": "GetLicensePlateIntent",
                    "samples": [
            "welches nummernschild habe ich",
            "welches nummernschild hat mein mercedes",
            "welches nummernschild hat mein auto",
            "sage mir mein nummernschild"
          ]
        },
                {
                    "name": "GetMilesIntent",
                    "samples": [
            "wie viele kilometer bin ich gefahren",
            "was ist der odometer stand",
            "was ist der kilometerstand",
            "sag mir den kilometerstand",
            "what is the odometer value"
          ]
        },
                {
                    "name": "LockDoorIntent",
                    "samples": [
            "sperre die türen",
            "sperre die tür",
            "schließe die türen ab",
            "schließe die tür ab",
            "schließe das auto ab",
            "schließe meinen mercedes ab",
            "sperre die türen ab",
            "sperre meinen mercedes ab",
            "sperre das auto ab",
            "sperre die tür ab"
          ]
        },
                {
                    "name": "UnlockDoorIntent",
                    "samples": [
            "öffne das auto",
            "öffne die tür",
            "öffne die türen",
            "schließe das auto auf",
            "schließe mein auto auf",
            "schließe die türen auf",
            "schließe meinen mercedes auf",
            "entsperre meinen mercedes",
            "entsperre mein auto",
            "entsperre mein fahrzeug",
            "entriegel die türen",
            "entriegel das auto",
            "entriegel das fahrzeug"
          ]
        },
                {
                    "name": "GetDoorStatusIntent",
                    "samples": [
            "welche türen sind geöffnet",
            "welche türen sind geschlossen",
            "welche türen sind gesperrt",
            "welche türen sind verriegelt",
            "welche türen sind entriegelt",
            "wie viele türen sind geöffnet",
            "wie viele türen sind geschlossen",
            "wie viele türen sind gesperrt",
            "wie viele türen sind entriegelt",
            "wie viele türen sind verriegelt",
            "ist das auto geöffnet",
            "ist das auto geschlossen",
            "ist das auto gesperrt",
            "ist das auto verriegelt",
            "ist das auto entriegelt",
            "ist mein mercedes geöffnet",
            "ist mein mercedes geschlossen",
            "ist mein mercedes gesperrt",
            "ist mein auto abgeschlossen",
            "ist mein mercedes abgeschlossen",
            "ist mein mercedes verriegelt",
            "ist mein mercedes entriegelt"
          ]
        },
                {
                    "name": "GetLocationIntent",
                    "samples": [
            "wo ist mein auto",
            "wo ist das auto",
            "wo ist mein mercedes",
            "wo bist du",
            "was ist die aktuelle position des autos",
            "was ist die aktuelle position",
            "wo bist du gerade"
          ]
        }
      ]
        }
    }
}
